[
  {
    "chamber_slug": "hwk-dortmund",
    "chamber_name": "HWK Dortmund",
    "chamber_region": "Nordrhein-Westfalen",
    "trade_slug": "allgemein-teil-iii-iv",
    "trade_name": "Wirtschaft, Recht, Pädagogik",
    "title": "Berufs- und Arbeitspädagogik (Teil IV)",
    "parts": [
      4
    ],
    "format": "full_time",
    "format_display": "Vollzeit",
    "teaching_mode": "online",
    "start_date": "2025-01-06",
    "end_date": "2025-01-24",
    "start_date_note": "",
    "duration_hours": null,
    "course_fee": null,
    "course_fee_display": "—",
    "exam_fee_scraped": null,
    "exam_fee_qualifier": "",
    "exam_fee": {
      "fee": 220.0,
      "fee_max": null,
      "qualifier": "",
      "display": "220 €",
      "from_tariff": true
    },
    "city": "Dortmund",
    "street": "Schützenstraße 32-34",
    "zip_code": "44147",
    "latitude": 51.5206367,
    "longitude": 7.4529522,
    "availability": "unknown",
    "source_url": "https://www.hwk-do.de/event/seminar/meisterkurse-geruestbauer/ausbildung-der-ausbilder-nach-der-aevo-der-sozialkasse/"
  },
  {
    "chamber_slug": "hwk-dortmund",
    "chamber_name": "HWK Dortmund",
    "chamber_region": "Nordrhein-Westfalen",
    "trade_slug": "allgemein-teil-iii-iv",
    "trade_name": "Wirtschaft, Recht, Pädagogik",
    "title": "Wirtschaft und Recht (Teil III)",
    "parts": [
      3
    ],
    "format": "full_time",
    "format_display": "Vollzeit",
    "teaching_mode": "presence",
    "start_date": "2026-07-20",
    "end_date": "2026-09-15",
    "start_date_note": "",
    "duration_hours": 300,
    "course_fee": 1985.0,
    "course_fee_display": "1.985 €",
    "exam_fee_scraped": 260.0,
    "exam_fee_qualifier": "",
    "exam_fee": {
      "fee": 260.0,
      "fee_max": null,
      "qualifier": "",
      "display": "260 €",
      "from_tariff": false
    },
    "city": "Dortmund",
    "street": "Schützenstraße 32-34",
    "zip_code": "44147",
    "latitude": 51.5206367,
    "longitude": 7.4529522,
    "availability": "available",
    "source_url": "https://www.hwk-do.de/event/seminar/weiterbildungsdatenbanken/gepr-fachmann-frau-fuer-kaufmaennische-betriebsfuehrung-hwo-vollzeit/"
  },
  {
    "chamber_slug": "hwk-karlsruhe",
    "chamber_name": "HWK Karlsruhe",
    "chamber_region": "Baden-Württemberg",
    "trade_slug": "kfz-techniker",
    "trade_name": "Kfz.-Techniker",
    "title": "Kfz.-Techniker (Teile I + II)",
    "parts": [
      1,
      2
    ],
    "format": "part_time",
    "format_display": "Teilzeit",
    "teaching_mode": "presence",
    "start_date": "2026-02-01",
    "end_date": "2026-12-31",
    "start_date_note": "",
    "duration_hours": null,
    "course_fee": 4200.0,
    "course_fee_display": "4.200 €",
    "exam_fee_scraped": null,
    "exam_fee_qualifier": "",
    "exam_fee": {
      "fee": 750.0,
      "fee_max": null,
      "qualifier": "",
      "display": "750 €",
      "from_tariff": true
    },
    "city": "Nagold",
    "street": "Max-Eyth-Straße 23",
    "zip_code": "72202",
    "latitude": 48.5473835,
    "longitude": 8.7138169,
    "availability": "available",
    "source_url": "https://www.handwerk-calw.de/seminare/termindetails/meistervorbereitungskurs-teil-4-fuer-alle-handwerke-1"
  },
  {
    "chamber_slug": "hwk-kassel",
    "chamber_name": "HWK Kassel",
    "chamber_region": "Hessen",
    "trade_slug": "fleischer",
    "trade_name": "Fleischer",
    "title": "Fleischer (Teile I + II)",
    "parts": [
      1,
      2
    ],
    "format": "full_time",
    "format_display": "Vollzeit",
    "teaching_mode": "presence",
    "start_date": "2026-06-29",
    "end_date": "2026-08-07",
    "start_date_note": "",
    "duration_hours": 300,
    "course_fee": null,
    "course_fee_display": "—",
    "exam_fee_scraped": null,
    "exam_fee_qualifier": "",
    "exam_fee": {
      "fee": 730.0,
      "fee_max": null,
      "qualifier": "",
      "display": "730 €",
      "from_tariff": true
    },
    "city": "Kassel",
    "street": "Falderbaumstraße 18-20",
    "zip_code": "34123",
    "latitude": 51.2841009,
    "longitude": 9.498614,
    "availability": "available",
    "source_url": "https://www.bz-kassel.de/bildungsangebot/fleischerhandwerk/kursdetail/kurs-1236"
  },
  {
    "chamber_slug": "hwk-kassel",
    "chamber_name": "HWK Kassel",
    "chamber_region": "Hessen",
    "trade_slug": "installateur-und-heizungsbauer",
    "trade_name": "Installateur- und Heizungsbauer",
    "title": "Installateur- und Heizungsbauer (Teile I + II + IV)",
    "parts": [
      1,
      2,
      4
    ],
    "format": "full_time",
    "format_display": "Vollzeit",
    "teaching_mode": "presence",
    "start_date": "2026-07-20",
    "end_date": "2027-03-02",
    "start_date_note": "",
    "duration_hours": 1245,
    "course_fee": 9930.0,
    "course_fee_display": "9.930 €",
    "exam_fee_scraped": null,
    "exam_fee_qualifier": "",
    "exam_fee": {
      "fee": 1075.0,
      "fee_max": null,
      "qualifier": "",
      "display": "1.075 €",
      "from_tariff": true
    },
    "city": "Marburg",
    "street": "Umgehungsstraße 1-3",
    "zip_code": "35043",
    "latitude": 50.7872688,
    "longitude": 8.7666044,
    "availability": "available",
    "source_url": "https://www.bbz-marburg.de/kurs/mv-shk-vz/"
  },
  {
    "chamber_slug": "hwk-konstanz",
    "chamber_name": "HWK Konstanz",
    "chamber_region": "Baden-Württemberg",
    "trade_slug": "elektrotechniker",
    "trade_name": "Elektrotechniker",
    "title": "Elektrotechniker (Teile I + II)",
    "parts": [
      1,
      2
    ],
    "format": "full_time",
    "format_display": "Vollzeit",
    "teaching_mode": "presence",
    "start_date": "2026-07-06",
    "end_date": "2027-01-27",
    "start_date_note": "",
    "duration_hours": 1269,
    "course_fee": 7250.0,
    "course_fee_display": "7.250 €",
    "exam_fee_scraped": 2050.0,
    "exam_fee_qualifier": "",
    "exam_fee": {
      "fee": 2050.0,
      "fee_max": null,
      "qualifier": "",
      "display": "2.050 €",
      "from_tariff": false
    },
    "city": "Singen",
    "street": "Lange Straße 20",
    "zip_code": "78224",
    "latitude": 47.7546664,
    "longitude": 8.8426339,
    "availability": "available",
    "source_url": "https://www.bildungsakademie.de/seminar/mv_elektro/#uni-kurs-1001020"
  },
  {
    "chamber_slug": "hwk-niederbayern-oberpfalz",
    "chamber_name": "HWK Niederbayern-Oberpfalz",
    "chamber_region": "Bayern",
    "trade_slug": "allgemein-teil-iii-iv",
    "trade_name": "Wirtschaft, Recht, Pädagogik",
    "title": "Berufs- und Arbeitspädagogik (Teil IV) — Straubing",
    "parts": [
      4
    ],
    "format": "full_time",
    "format_display": "Vollzeit",
    "teaching_mode": "presence",
    "start_date": "2026-07-13",
    "end_date": "2026-07-24",
    "start_date_note": "",
    "duration_hours": 80,
    "course_fee": 565.0,
    "course_fee_display": "565 €",
    "exam_fee_scraped": null,
    "exam_fee_qualifier": "",
    "exam_fee": {
      "fee": null,
      "fee_max": null,
      "qualifier": "",
      "display": "",
      "from_tariff": false
    },
    "city": "Straubing",
    "street": "Johannes-Kepler-Straße 14",
    "zip_code": "94315",
    "latitude": 48.8708639,
    "longitude": 12.5760232,
    "availability": "full",
    "source_url": "https://www.hwkno.de/76,0,coursedetail.html?id=1009331"
  },
  {
    "chamber_slug": "hwk-niederbayern-oberpfalz",
    "chamber_name": "HWK Niederbayern-Oberpfalz",
    "chamber_region": "Bayern",
    "trade_slug": "allgemein-teil-iii-iv",
    "trade_name": "Wirtschaft, Recht, Pädagogik",
    "title": "Berufs- und Arbeitspädagogik (Teil IV) — Landshut",
    "parts": [
      4
    ],
    "format": "full_time",
    "format_display": "Vollzeit",
    "teaching_mode": "presence",
    "start_date": "2026-07-13",
    "end_date": "2026-07-24",
    "start_date_note": "",
    "duration_hours": 80,
    "course_fee": 565.0,
    "course_fee_display": "565 €",
    "exam_fee_scraped": null,
    "exam_fee_qualifier": "",
    "exam_fee": {
      "fee": null,
      "fee_max": null,
      "qualifier": "",
      "display": "",
      "from_tariff": false
    },
    "city": "Landshut",
    "street": "Am Lurzenhof 10 b",
    "zip_code": "84036",
    "latitude": 48.5594648,
    "longitude": 12.1999128,
    "availability": "full",
    "source_url": "https://www.hwkno.de/76,0,coursedetail.html?id=1011422"
  },
  {
    "chamber_slug": "hwk-suedwestfalen",
    "chamber_name": "HWK Südwestfalen",
    "chamber_region": "Nordrhein-Westfalen",
    "trade_slug": "allgemein-teil-iii-iv",
    "trade_name": "Wirtschaft, Recht, Pädagogik",
    "title": "Berufs- und Arbeitspädagogik (Teil IV)",
    "parts": [
      4
    ],
    "format": "part_time",
    "format_display": "Teilzeit",
    "teaching_mode": "presence",
    "start_date": "2026-07-20",
    "end_date": "2026-08-07",
    "start_date_note": "",
    "duration_hours": 120,
    "course_fee": 650.0,
    "course_fee_display": "650 €",
    "exam_fee_scraped": 275.0,
    "exam_fee_qualifier": "",
    "exam_fee": {
      "fee": 275.0,
      "fee_max": null,
      "qualifier": "",
      "display": "275 €",
      "from_tariff": false
    },
    "city": "Arnsberg",
    "street": "Im Hülsenfeld 42",
    "zip_code": "59755",
    "latitude": 51.4470454,
    "longitude": 7.9631509,
    "availability": "available",
    "source_url": "https://www.bbz-arnsberg.de/kurse/ausbildung-der-ausbilder-nach-aevo#termin-1"
  },
  {
    "chamber_slug": "hwk-suedwestfalen",
    "chamber_name": "HWK Südwestfalen",
    "chamber_region": "Nordrhein-Westfalen",
    "trade_slug": "allgemein-teil-iii-iv",
    "trade_name": "Wirtschaft, Recht, Pädagogik",
    "title": "Wirtschaft und Recht (Teil III)",
    "parts": [
      3
    ],
    "format": "part_time",
    "format_display": "Teilzeit",
    "teaching_mode": "presence",
    "start_date": "2026-07-21",
    "end_date": "2026-09-04",
    "start_date_note": "",
    "duration_hours": 300,
    "course_fee": 1810.0,
    "course_fee_display": "1.810 €",
    "exam_fee_scraped": 275.0,
    "exam_fee_qualifier": "",
    "exam_fee": {
      "fee": 275.0,
      "fee_max": null,
      "qualifier": "",
      "display": "275 €",
      "from_tariff": false
    },
    "city": "Arnsberg",
    "street": "Im Hülsenfeld 42",
    "zip_code": "59755",
    "latitude": 51.4470454,
    "longitude": 7.9631509,
    "availability": "available",
    "source_url": "https://www.bbz-arnsberg.de/kurse/gepruefte-r-fachfrau-fachmann-fuer-kaufmaennische-betriebsfuehrung-hwo#termin-1"
  },
  {
    "chamber_slug": "hwk-unterfranken",
    "chamber_name": "HWK für Unterfranken",
    "chamber_region": "Bayern",
    "trade_slug": "allgemein-teil-iii-iv",
    "trade_name": "Wirtschaft, Recht, Pädagogik",
    "title": "Berufs- und Arbeitspädagogik (Teil IV)",
    "parts": [
      4
    ],
    "format": "part_time",
    "format_display": "Teilzeit",
    "teaching_mode": "online",
    "start_date": "2026-07-18",
    "end_date": "2026-10-13",
    "start_date_note": "",
    "duration_hours": 115,
    "course_fee": 990.0,
    "course_fee_display": "990 €",
    "exam_fee_scraped": null,
    "exam_fee_qualifier": "",
    "exam_fee": {
      "fee": 165.0,
      "fee_max": null,
      "qualifier": "",
      "display": "165 €",
      "from_tariff": true
    },
    "city": "Online",
    "street": "",
    "zip_code": "",
    "latitude": 49.1249172,
    "longitude": 10.7805332,
    "availability": "waitlist",
    "source_url": "https://www.hwk-ufr.de/78,0,coursedetail.html?id=449041"
  }
]
